pgdatacleaner/__init__.py
pgdatacleaner/cleaner.py
pgdatacleaner/datadict.py
pgdatacleaner-1.1.0a16.dist-info/entry_points.txt
pgdatacleaner-1.1.0a16.dist-info/WHEEL
pgdatacleaner-1.1.0a16.dist-info/METADATA
pgdatacleaner-1.1.0a16.dist-info/RECORD
