Metadata-Version: 2.1
Name: pgdatacleaner
Version: 1.1.0a16
Summary: Data cleaning/masking for PostgreSQL databases
License: MIT
Author: Fredrik Håård
Author-email: fredrik@metallapan.se
Requires-Python: >=3.7,<4
Classifier: License :: OSI Approved :: MIT License
Classifier: Programming Language :: Python :: 3
Classifier: Programming Language :: Python :: 3.7
Classifier: Programming Language :: Python :: 3.8
Classifier: Programming Language :: Python :: 3.9
Requires-Dist: Faker (>=8.12.1,<9.0.0)
Requires-Dist: psycopg2-binary (>2.8.0,<2.10)
Requires-Dist: python-slugify (>=5.0.2,<6.0.0)
